playwrightcapture/__init__.py
playwrightcapture/capture.py
playwrightcapture/exceptions.py
playwrightcapture/helpers.py
playwrightcapture/py.typed
playwrightcapture/socks5dnslookup.py
playwrightcapture-1.36.4.dist-info/METADATA
playwrightcapture-1.36.4.dist-info/WHEEL
playwrightcapture-1.36.4.dist-info/licenses/LICENSE
playwrightcapture-1.36.4.dist-info/RECORD
