Metadata-Version: 2.4
Name: PlaywrightCapture
Version: 1.36.4
Summary: A simple library to capture websites using playwright
License-Expression: BSD-3-Clause
License-File: LICENSE
Author: Raphaël Vinot
Author-email: raphael.vinot@circl.lu
Requires-Python: >=3.10,<4.0
Classifier: Intended Audience :: Science/Research
Classifier: Intended Audience :: Telecommunications Industry
Classifier: Programming Language :: Python :: 3
Classifier: Programming Language :: Python :: 3.10
Classifier: Programming Language :: Python :: 3.11
Classifier: Programming Language :: Python :: 3.12
Classifier: Programming Language :: Python :: 3.13
Classifier: Programming Language :: Python :: 3.14
Classifier: Topic :: Internet
Classifier: Topic :: Security
Provides-Extra: recaptcha
Requires-Dist: SpeechRecognition (>=3.14.5) ; extra == "recaptcha"
Requires-Dist: aiohttp-socks (>=0.11.0)
Requires-Dist: aiohttp[speedups] (>=3.13.3)
Requires-Dist: async-timeout (>=5.0.1) ; python_version < "3.11"
Requires-Dist: beautifulsoup4[charset-normalizer,lxml] (>=4.14.3)
Requires-Dist: dateparser (>=1.2.2)
Requires-Dist: dnspython (>=2.7.0,<3.0.0)
Requires-Dist: orjson (>=3.11.4,<4.0.0)
Requires-Dist: playwright (>=1.58.0)
Requires-Dist: playwright-stealth (>=2.0.1)
Requires-Dist: puremagic (>=1.30)
Requires-Dist: pydub-ng (>=0.2.0) ; extra == "recaptcha"
Requires-Dist: python-socks (>=2.7.1,<3.0.0)
Requires-Dist: rfc3161-client (>=1.0.4,<2.0.0)
Requires-Dist: setuptools (>=80.10.2)
Requires-Dist: typing-extensions (>=4.12.2,<5.0.0) ; python_version < "3.12"
Requires-Dist: tzdata (>=2025.3)
Requires-Dist: w3lib (>=2.4.0)
Project-URL: Issues, https://github.com/Lookyloo/PlaywrightCapture/issues
Project-URL: Repository, https://github.com/Lookyloo/PlaywrightCapture
